{
  "runs": 11,
  "total_incidents": 51,
  "areas": {
    "Hyderi": 4,
    "DHA": 12,
    "Faisal on Saturday night": 4,
    "Nipa": 4,
    "Saddar": 4,
    "Malir": 10,
    "Bahadurabad": 3,
    "Korangi": 1,
    "Rizvia Society": 3,
    "Garden": 1,
    "Syed Murad Ali Shah directed": 2,
    "Karachi in Dubai": 2,
    "Jamshed Quarters": 1
  },
  "sources": {
    "Dawn": {
      "count": 48,
      "quality_scores": [
        1.0,
        0.7,
        0.8500000000000001,
        1.0,
        1.0,
        1.0,
        1.0,
        0.8,
        0.8999999999999999,
        1.0,
        1.0,
        0.8999999999999999,
        0.8,
        1.0,
        0.75,
        0.7,
        0.8500000000000001,
        0.8999999999999999,
        0.8,
        0.8999999999999999,
        0.8999999999999999,
        0.8,
        0.8,
        0.8,
        0.8999999999999999,
        0.7,
        0.8500000000000001,
        0.8999999999999999,
        0.8999999999999999,
        0.8,
        0.8,
        0.8,
        1.0,
        0.8999999999999999,
        1.0,
        0.8999999999999999,
        0.8,
        0.7,
        0.8500000000000001,
        0.8,
        0.8,
        0.8,
        1.0,
        0.8999999999999999,
        1.0,
        1.0,
        0.8999999999999999,
        0.8999999999999999
      ],
      "avg_quality": 0.8760416666666663,
      "success_rate": 1.0,
      "last_success": "2025-12-05T11:36:10.936415",
      "failure_count": 0
    },
    "Google News": {
      "count": 3,
      "quality_scores": [
        0.7,
        0.75,
        0.75
      ],
      "avg_quality": 0.7333333333333334,
      "success_rate": 1.0,
      "last_success": "2025-12-01T12:14:28.195572",
      "failure_count": 0
    }
  },
  "successful_queries": [],
  "failed_queries": [
    "DHA mobile snatching karachi",
    "DHA phone theft karachi",
    "mobile snatched DHA karachi",
    "Clifton mobile snatching karachi",
    "Clifton phone theft karachi",
    "Hyderi mobile snatching karachi",
    "Hyderi phone theft karachi",
    "mobile snatched Hyderi karachi",
    "Faisal on Saturday night mobile snatching karachi",
    "Faisal on Saturday night phone theft karachi",
    "mobile snatched Faisal on Saturday night karachi",
    "FB Area Block 2 mobile snatching karachi",
    "Korangi No. 3 mobile snatching karachi",
    "Korangi No. 4 mobile snatching karachi",
    "Surjani Town Sector 3 mobile snatching karachi",
    "Merewether Tower mobile snatching karachi",
    "Nipa mobile snatching karachi",
    "Nipa phone theft karachi",
    "mobile snatched Nipa karachi",
    "Saddar mobile snatching karachi",
    "Saddar phone theft karachi",
    "mobile snatched Saddar karachi",
    "Malir mobile snatching karachi",
    "Malir phone theft karachi",
    "mobile snatched Malir karachi",
    "Bahadurabad mobile snatching karachi",
    "Bahadurabad phone theft karachi",
    "mobile snatched Bahadurabad karachi",
    "Baldia No. 1 mobile snatching karachi",
    "Korangi No. 2 mobile snatching karachi",
    "Orangi No. 5 mobile snatching karachi",
    "Liaquatabad No. 3 mobile snatching karachi",
    "North Karachi Buffer Zone mobile snatching karachi",
    "Nazimabad Block 3 mobile snatching karachi",
    "DHA Phase 5 mobile snatching karachi",
    "Sohrab Goth mobile snatching karachi",
    "Gulshan Block 11 mobile snatching karachi",
    "Gulshan Block 4 mobile snatching karachi",
    "Gulshan mobile snatching karachi",
    "Liaquatabad No. 8 mobile snatching karachi",
    "Lyari Expressway mobile snatching karachi",
    "Korangi mobile snatching karachi",
    "Korangi phone theft karachi",
    "mobile snatched Korangi karachi",
    "North Nazimabad mobile snatching karachi",
    "Keamari mobile snatching karachi",
    "Sea View mobile snatching karachi",
    "Saddar Cantt mobile snatching karachi",
    "Clifton Block 7 mobile snatching karachi",
    "Rizvia Society mobile snatching karachi",
    "Rizvia Society phone theft karachi",
    "mobile snatched Rizvia Society karachi",
    "Garden mobile snatching karachi",
    "Garden phone theft karachi",
    "mobile snatched Garden karachi",
    "Karachi in Dubai mobile snatching karachi",
    "Karachi in Dubai phone theft karachi",
    "mobile snatched Karachi in Dubai karachi"
  ],
  "selector_performance": {},
  "verified_sources": [
    "dawn.com",
    "geo.tv",
    "tribune.com.pk",
    "express.com.pk",
    "thenews.com.pk",
    "karachipoliceonline",
    "sindhpolice.gov.pk",
    "twitter.com/sindhpolice",
    "facebook.com/sindhpolice"
  ],
  "granular_areas": [
    "DHA",
    "DHA Phase 1",
    "DHA Phase 2",
    "DHA Phase 3",
    "DHA Phase 4",
    "DHA Phase 5",
    "DHA Phase 6",
    "DHA Phase 7",
    "DHA Phase 8",
    "Defence",
    "Clifton",
    "Clifton Block 1",
    "Clifton Block 2",
    "Clifton Block 3",
    "Clifton Block 4",
    "Clifton Block 5",
    "Clifton Block 6",
    "Clifton Block 7",
    "Clifton Block 8",
    "Clifton Block 9",
    "Boat Basin",
    "Zamzama",
    "Sea View",
    "Do Darya",
    "Gulshan-e-Iqbal",
    "Gulshan",
    "Gulshan Block 1",
    "Gulshan Block 2",
    "Gulshan Block 3",
    "Gulshan Block 4",
    "Gulshan Block 5",
    "Gulshan Block 6",
    "Gulshan Block 7",
    "Gulshan Block 8",
    "Gulshan Block 9",
    "Gulshan Block 10",
    "Gulshan Block 11",
    "Gulshan Block 12",
    "Gulshan Block 13",
    "Gulshan Block 14",
    "Gulshan Block 15",
    "Gulistan-e-Johar",
    "Gulistan-e-Johar Block 1",
    "Gulistan-e-Johar Block 2",
    "Gulistan-e-Johar Block 3",
    "Gulistan-e-Johar Block 4",
    "Gulistan-e-Johar Block 5",
    "Gulistan-e-Johar Block 6",
    "Gulistan-e-Johar Block 7",
    "Gulistan-e-Johar Block 8",
    "Gulistan-e-Johar Block 9",
    "Gulistan-e-Johar Block 10",
    "Nazimabad",
    "Nazimabad Block 1",
    "Nazimabad Block 2",
    "Nazimabad Block 3",
    "Nazimabad Block 4",
    "Nazimabad Block 5",
    "Nazimabad Block 6",
    "North Nazimabad",
    "Nazimabad No. 1",
    "Nazimabad No. 2",
    "Federal B Area",
    "FB Area",
    "FB Area Block 1",
    "FB Area Block 2",
    "FB Area Block 3",
    "FB Area Block 4",
    "FB Area Block 5",
    "FB Area Block 6",
    "FB Area Block 7",
    "FB Area Block 8",
    "FB Area Block 9",
    "FB Area Block 10",
    "FB Area Block 11",
    "FB Area Block 12",
    "FB Area Block 13",
    "FB Area Block 14",
    "FB Area Block 15",
    "FB Area Block 16",
    "FB Area Block 17",
    "FB Area Block 18",
    "FB Area Block 19",
    "FB Area Block 20",
    "Korangi",
    "Korangi No. 1",
    "Korangi No. 2",
    "Korangi No. 3",
    "Korangi No. 4",
    "Korangi No. 5",
    "Korangi No. 6",
    "Korangi Industrial Area",
    "Korangi Crossing",
    "Korangi Creek",
    "Landhi",
    "Landhi No. 1",
    "Landhi No. 2",
    "Landhi No. 3",
    "Landhi No. 4",
    "Landhi No. 5",
    "Landhi No. 6",
    "Landhi Industrial Area",
    "Malir",
    "Malir Cantt",
    "Malir City",
    "Malir Halt",
    "Malir Colony",
    "Shah Faisal Colony",
    "Jinnah Terminal",
    "Airport",
    "North Karachi",
    "North Karachi Sector 5",
    "North Karachi Sector 7",
    "North Karachi Sector 11",
    "North Karachi Buffer Zone",
    "New Karachi",
    "New Karachi Sector 5",
    "New Karachi Sector 11",
    "Saddar",
    "Saddar Town",
    "Empress Market",
    "Regal Chowk",
    "Merewether Tower",
    "Garden",
    "Garden East",
    "Garden West",
    "PECHS",
    "PECHS Block 2",
    "PECHS Block 3",
    "PECHS Block 6",
    "Bahadurabad",
    "Shahrah-e-Faisal",
    "Liaquatabad",
    "Liaquatabad No. 1",
    "Liaquatabad No. 2",
    "Liaquatabad No. 3",
    "Liaquatabad No. 4",
    "Liaquatabad No. 5",
    "Liaquatabad No. 6",
    "Liaquatabad No. 7",
    "Liaquatabad No. 8",
    "Liaquatabad No. 9",
    "Liaquatabad No. 10",
    "Orangi",
    "Orangi Town",
    "Orangi No. 1",
    "Orangi No. 2",
    "Orangi No. 3",
    "Orangi No. 4",
    "Orangi No. 5",
    "Baldia",
    "Baldia Town",
    "Baldia No. 1",
    "Baldia No. 2",
    "Baldia No. 3",
    "Lyari",
    "Lyari Town",
    "Lyari Expressway",
    "Keamari",
    "Keamari Town",
    "Kemari",
    "SITE",
    "SITE Area",
    "SITE Industrial Area",
    "SITE Super Highway",
    "Surjani Town",
    "Surjani Town Sector 1",
    "Surjani Town Sector 2",
    "Surjani Town Sector 3",
    "Surjani Town Sector 4",
    "Surjani Town Sector 5",
    "Scheme 33",
    "Gulzar-e-Hijri",
    "Tariq Road",
    "Soldier Bazaar",
    "Model Colony",
    "Buffer Zone",
    "Sohrab Goth",
    "Gulberg",
    "Gulberg Town",
    "Kharadar",
    "Mithadar",
    "Jamshed Town",
    "Jamshed Road",
    "Pak Colony",
    "Manzoor Colony",
    "Mehmoodabad",
    "Mehmoodabad No. 1",
    "Mehmoodabad No. 2",
    "Azizabad",
    "Karimabad",
    "Hyderi",
    "Quaidabad",
    "Saudabad",
    "University Road",
    "Jail Road",
    "Rashid Minhas Road",
    "Drigh Road",
    "Korangi Road",
    "Karsaz",
    "Nipa",
    "Nipa Chowrangi",
    "Safora",
    "Safora Goth",
    "Shahra-e-Pakistan",
    "Mauripur",
    "Hawksbay",
    "Manghopir",
    "Bin Qasim",
    "Bin Qasim Town",
    "Gadap",
    "Gadap Town",
    "Saddar Cantt",
    "Cantonment",
    "Faisal Cantonment",
    "Faisal on Saturday night",
    "Rizvia Society",
    "Syed Murad Ali Shah directed",
    "Karachi in Dubai",
    "Jamshed Quarters"
  ],
  "discovered_facebook_pages": [],
  "discovered_facebook_groups": []
}